wagtailextraicons/__init__.py
wagtailextraicons/apps.py
wagtailextraicons/icon_register.py
wagtailextraicons/wagtail_hooks.py
wagtailextraicons/templates/extraicons/.keep
wagtailextraicons/templates/extraicons/extraicons--2-col-heading-text.svg
wagtailextraicons/templates/extraicons/extraicons--2-col-lg.svg
wagtailextraicons/templates/extraicons/extraicons--2-col-paragraph.svg
wagtailextraicons/templates/extraicons/extraicons--2-col-right-small.svg
wagtailextraicons/templates/extraicons/extraicons--2-col-video.svg
wagtailextraicons/templates/extraicons/extraicons--2-col-with-links.svg
wagtailextraicons/templates/extraicons/extraicons--2-col.svg
wagtailextraicons/templates/extraicons/extraicons--3-col-links.svg
wagtailextraicons/templates/extraicons/extraicons--3-col.svg
wagtailextraicons/templates/extraicons/extraicons--4-col-heading.svg
wagtailextraicons/templates/extraicons/extraicons--4-col.svg
wagtailextraicons/templates/extraicons/extraicons--banner.svg
wagtailextraicons/templates/extraicons/extraicons--basic-field.svg
wagtailextraicons/templates/extraicons/extraicons--block-quote.svg
wagtailextraicons/templates/extraicons/extraicons--button.svg
wagtailextraicons/templates/extraicons/extraicons--cards.svg
wagtailextraicons/templates/extraicons/extraicons--checkbox.svg
wagtailextraicons/templates/extraicons/extraicons--checkboxes.svg
wagtailextraicons/templates/extraicons/extraicons--cta-inverted.svg
wagtailextraicons/templates/extraicons/extraicons--cta-with-button.svg
wagtailextraicons/templates/extraicons/extraicons--cta.svg
wagtailextraicons/templates/extraicons/extraicons--date.svg
wagtailextraicons/templates/extraicons/extraicons--dropdown.svg
wagtailextraicons/templates/extraicons/extraicons--email.svg
wagtailextraicons/templates/extraicons/extraicons--heading-icon.svg
wagtailextraicons/templates/extraicons/extraicons--hidden.svg
wagtailextraicons/templates/extraicons/extraicons--image-gallery.svg
wagtailextraicons-3.0.0.dist-info/LICENSE.txt
wagtailextraicons-3.0.0.dist-info/METADATA
wagtailextraicons-3.0.0.dist-info/WHEEL
wagtailextraicons-3.0.0.dist-info/top_level.txt
wagtailextraicons-3.0.0.dist-info/RECORD
