Metadata-Version: 2.1
Name: wagtailextraicons
Version: 3.0.0
Summary: Add extra icons to your Wagtail project.
Home-page: https://github.com/octavenz/wagtailextraicons
Author: Sam Costigan (Octave)
Author-email: support@octave.nz
License: BSD-3-Clause
Classifier: Environment :: Web Environment
Classifier: Intended Audience :: Developers
Classifier: License :: OSI Approved :: BSD License
Classifier: Framework :: Wagtail :: 3
Classifier: Framework :: Wagtail :: 4
Classifier: Operating System :: OS Independent
Classifier: Programming Language :: Python :: 3
Classifier: Topic :: Internet :: WWW/HTTP
Classifier: Topic :: Internet :: WWW/HTTP :: Site Management
License-File: LICENSE.txt
Requires-Dist: wagtail (>=3.0)
